github_api.py
my_first_package_liniker-0.1.dist-info/LICENSE
my_first_package_liniker-0.1.dist-info/METADATA
my_first_package_liniker-0.1.dist-info/WHEEL
my_first_package_liniker-0.1.dist-info/top_level.txt
my_first_package_liniker-0.1.dist-info/RECORD
