Metadata-Version: 2.1
Name: my-first-package-liniker
Version: 0.1
Summary: Get your avatar on GitHub
Home-page: https://github.com/linikerunk/libpythonpro.git
Author: Liniker Oliveira
Author-email: linikerenem@gmail.com
License: UNKNOWN
Platform: UNKNOWN
Classifier: Development Status :: 3 - Alpha
Classifier: Environment :: Console 
Classifier: Intended Audience :: Developers
Classifier: License :: Aladdin Free Public License (AFPL)
Classifier: Operating System :: OS Independent
Classifier: Programming Language :: Python :: 3.8
Classifier: Framework :: Pytest
